pyphs/__init__.py
pyphs/config.py
pyphs/core/__init__.py
pyphs/core/core.py
pyphs/core/maths/__init__.py
pyphs/core/maths/_calculus.py
pyphs/core/maths/_matrices.py
pyphs/core/maths/_vectors.py
pyphs/core/structure/R.py
pyphs/core/structure/__init__.py
pyphs/core/structure/connectors.py
pyphs/core/structure/dimensions.py
pyphs/core/structure/indices.py
pyphs/core/structure/moves.py
pyphs/core/structure/output.py
pyphs/core/structure/splits.py
pyphs/core/tools/__init__.py
pyphs/core/tools/_free_symbols.py
pyphs/core/tools/_simplify.py
pyphs/core/tools/_subsinverse.py
pyphs/core/tools/_substitutions.py
pyphs/core/tools/_types.py
pyphs/dictionary/__init__.py
pyphs/dictionary/tools.py
pyphs/dictionary/beams/__init__.py
pyphs/dictionary/beams/_cantilever.py
pyphs/dictionary/connectors/__init__.py
pyphs/dictionary/connectors/_gyrator.py
pyphs/dictionary/connectors/_transformer.py
pyphs/dictionary/edges/__init__.py
pyphs/dictionary/edges/connectors.py
pyphs/dictionary/edges/dissipatives.py
pyphs/dictionary/edges/generic.py
pyphs/dictionary/edges/observers.py
pyphs/dictionary/edges/port.py
pyphs/dictionary/edges/storages.py
pyphs/dictionary/electronics/__init__.py
pyphs/dictionary/electronics/_bjt.py
pyphs/dictionary/electronics/_capacitor.py
pyphs/dictionary/electronics/_diode.py
pyphs/dictionary/electronics/_inductor.py
pyphs/dictionary/electronics/_potentiometer.py
pyphs/dictionary/electronics/_resistor.py
pyphs/dictionary/electronics/_source.py
pyphs/dictionary/electronics/_triode.py
pyphs/dictionary/fraccalc/__init__.py
pyphs/dictionary/fraccalc/fractional_derivators.py
pyphs/dictionary/fraccalc/fractional_integrators.py
pyphs/dictionary/magnetics/__init__.py
pyphs/dictionary/magnetics/_capacitor.py
pyphs/dictionary/magnetics/_capacitorsat.py
pyphs/dictionary/magnetics/_resistor.py
pyphs/dictionary/magnetics/_source.py
pyphs/dictionary/mechanics/__init__.py
pyphs/dictionary/mechanics/_damper.py
pyphs-0.1.12.dist-info/DESCRIPTION.rst
pyphs-0.1.12.dist-info/METADATA
pyphs-0.1.12.dist-info/RECORD
pyphs-0.1.12.dist-info/WHEEL
pyphs-0.1.12.dist-info/metadata.json
pyphs-0.1.12.dist-info/top_level.txt
