Metadata-Version: 2.0
Name: pyphs
Version: 0.1.12
Summary: Development Status :: 4 - Beta
Home-page: https://github.com/pyphs/pyphs
Author: Antoine Falaize
Author-email: antoine.falaize@gmail.fr
License: CEA CNRS Inria Logiciel Libre License, version 2.1 (CeCILL-2.1)
Keywords: dynamical systems,numerical analysis,passive systems,port-hamiltonian systems,C++,Latex
Platform: UNKNOWN
Classifier: Natural Language :: English
Classifier: Development Status :: 4 - Beta
Classifier: Operating System :: Unix
Classifier: Operating System :: MacOS
Classifier: Operating System :: MacOS :: MacOS X
Classifier: Operating System :: Microsoft
Classifier: Operating System :: Microsoft :: Windows
Classifier: Programming Language :: Python :: 2
Classifier: Programming Language :: Python :: 2.7
Classifier: Programming Language :: Python :: 3
Classifier: Programming Language :: Python :: 3.5
Classifier: Programming Language :: Python :: 3.6
Classifier: Intended Audience :: Science/Research
Classifier: License :: OSI Approved :: CEA CNRS Inria Logiciel Libre License, version 2.1 (CeCILL-2.1)
Classifier: Topic :: Scientific/Engineering
Classifier: Topic :: Scientific/Engineering :: Physics
Requires-Dist: matplotlib (>=2.0.0)
Requires-Dist: networkx (>=1.11)
Requires-Dist: nose (>=1.3.7)
Requires-Dist: numpy (>=1.9.3)
Requires-Dist: progressbar2 (>=2.3)
Requires-Dist: scipy (>=0.16.0)
Requires-Dist: stopit (>=1.1.1)
Requires-Dist: sympy (>=1.1.1)
